{
  "parent": "minecraft:recipes/root",
  "criteria": {
    "has_ore": {
      "conditions": {
        "items": [
          {
            "items": [
              "dreamland:kunzite_copper_ore"
            ]
          }
        ]
      },
      "trigger": "minecraft:inventory_changed"
    },
    "has_the_recipe": {
      "conditions": {
        "recipe": "minecraft:kunzite_copper_to_ingot_blasting"
      },
      "trigger": "minecraft:recipe_unlocked"
    }
  },
  "requirements": [
    [
      "has_ore",
      "has_the_recipe"
    ]
  ],
  "rewards": {
    "recipes": [
      "minecraft:kunzite_copper_to_ingot_blasting"
    ]
  }
}