{
  "parent": "minecraft:recipes/root",
  "criteria": {
    "has_the_recipe": {
      "conditions": {
        "recipe": "dreamland:packed_tar_mud"
      },
      "trigger": "minecraft:recipe_unlocked"
    },
    "tar_mud": {
      "conditions": {
        "items": [
          {
            "items": [
              "dreamland:tar_mud"
            ]
          }
        ]
      },
      "trigger": "minecraft:inventory_changed"
    }
  },
  "requirements": [
    [
      "tar_mud",
      "has_the_recipe"
    ]
  ],
  "rewards": {
    "recipes": [
      "dreamland:packed_tar_mud"
    ]
  }
}